Metadata-Version: 2.1
Name: odoo14-addon-cooperator-account-payment
Version: 14.0.1.1.0
Summary: This module adds support for payment mode to cooperator.
Home-page: https://coopdevs.org
Author: Som IT Cooperatiu SCCL
License: AGPL-3
Classifier: Programming Language :: Python
Classifier: Framework :: Odoo
Classifier: Framework :: Odoo :: 14.0
Classifier: License :: OSI Approved :: GNU Affero General Public License v3
Requires-Python: >=3.6
Requires-Dist: odoo14-addon-account-payment-partner
Requires-Dist: odoo14-addon-cooperator
Requires-Dist: odoo (<14.1dev,>=14.0a)
